sensipy/__init__.py
sensipy/ctaoirf.py
sensipy/data/create_mock_data.py
sensipy/data/create_mock_lookup.py
sensipy/data/ebl/README.md
sensipy/data/ebl/ebl_dominguez11.fits.gz
sensipy/data/ebl/ebl_franceschini.fits.gz
sensipy/data/ebl/ebl_franceschini_2017.fits.gz
sensipy/data/ebl/ebl_models.png
sensipy/data/ebl/ebl_saldana-lopez_2021.fits.gz
sensipy/data/ebl/frd_abs.fits.gz
sensipy/data/mock_data/GRB_42_mock.csv
sensipy/data/mock_data/GRB_42_mock.fits
sensipy/data/mock_data/GRB_42_mock_metadata.csv
sensipy/data/mock_data/detectability_lookup.parquet
sensipy/data/mock_data/mock_lookup_table.parquet
sensipy/detectability.py
sensipy/followup.py
sensipy/logging.py
sensipy/scripts/__init__.py
sensipy/scripts/download_ctao_irfs.py
sensipy/sensitivity.py
sensipy/source.py
sensipy/util.py
sensipy-4.0b9.dist-info/licenses/LICENSE
sensipy-4.0b9.dist-info/WHEEL
sensipy-4.0b9.dist-info/entry_points.txt
sensipy-4.0b9.dist-info/METADATA
sensipy-4.0b9.dist-info/RECORD
