Metadata-Version: 2.4
Name: sensipy
Version: 4.0b9
Summary: A Python toolkit to simulate instrument sensitivity and plan follow-up observations of time-variable astrophysical sources with gamma-ray observatories.
Keywords: gamma-ray,astronomy,astrophysics,cherenkov,gamma-ray astronomy
Author: Jarred Green, Barbara Patricelli, Antonio Stamerra, Monica Seglar-Arroyo
Author-email: Jarred Green <jgreen@mpp.mpg.de>, Barbara Patricelli <barbara.patricelli@inaf.it>, Antonio Stamerra <antonio.stamerra@inaf.it>, Monica Seglar-Arroyo <mseglar@ifae.es>
License-Expression: Apache-2.0
License-File: LICENSE
Classifier: Development Status :: 5 - Production/Stable
Classifier: Intended Audience :: Science/Research
Classifier: License :: OSI Approved :: Apache Software License
Classifier: Operating System :: OS Independent
Classifier: Programming Language :: Python :: 3
Classifier: Programming Language :: Python :: 3.11
Classifier: Programming Language :: Python :: 3.12
Classifier: Programming Language :: Python :: 3.13
Classifier: Topic :: Scientific/Engineering :: Astronomy
Classifier: Topic :: Scientific/Engineering :: Physics
Requires-Dist: astropy>=6.0
Requires-Dist: matplotlib>=3.8
Requires-Dist: pandas>=2.3.3
Requires-Dist: pydantic>=2.12.0
Requires-Dist: scipy>=1.16.2
Requires-Dist: seaborn>=0.13.0
Requires-Dist: tqdm>=4.67.1
Requires-Dist: gammapy>=2.0
Requires-Dist: pyarrow>=21.0.0
Requires-Dist: numpy>=1.26.4
Requires-Dist: types-seaborn>=0.13.2.20250914
Requires-Dist: pandas-stubs>=2.3.2.250926
Requires-Dist: scipy-stubs>=1.16.3.0
Requires-Dist: pytest-xdist[psutil]>=3.8.0
Requires-Dist: types-tqdm>=4.67.0.20250809
Requires-Python: >=3.11
Project-URL: Documentation, https://sensipy.vercel.app/
Project-URL: Source, https://github.com/astrojarred/sensipy
Project-URL: Tracker, https://github.com/astrojarred/sensipy/issues
